tree_sitter_query/__init__.py
tree_sitter_query/__init__.pyi
tree_sitter_query/_binding.abi3.so
tree_sitter_query/binding.c
tree_sitter_query/py.typed
tree_sitter_query/queries/query/folds.scm
tree_sitter_query/queries/query/highlights.scm
tree_sitter_query/queries/query/injections.scm
tree_sitter_query-0.7.0.dist-info/METADATA
tree_sitter_query-0.7.0.dist-info/WHEEL
tree_sitter_query-0.7.0.dist-info/top_level.txt
tree_sitter_query-0.7.0.dist-info/RECORD
tree_sitter_query-0.7.0.dist-info/licenses/LICENSE
