Metadata-Version: 2.4
Name: tree-sitter-query
Version: 0.7.0
Summary: TS query grammar for tree-sitter
Author: Steven Sojka
License: Apache-2.0
Project-URL: Homepage, https://github.com/tree-sitter-grammars/tree-sitter-query
Keywords: incremental,parsing,tree-sitter,query
Classifier: Intended Audience :: Developers
Classifier: License :: OSI Approved :: Apache Software License
Classifier: Topic :: Software Development :: Compilers
Classifier: Topic :: Text Processing :: Linguistic
Classifier: Typing :: Typed
Requires-Python: >=3.10
License-File: LICENSE
Provides-Extra: core
Requires-Dist: tree-sitter~=0.25; extra == "core"
Dynamic: license-file
